README.md
setup.py
clustertree/__init__.py
clustertree.egg-info/PKG-INFO
clustertree.egg-info/SOURCES.txt
clustertree.egg-info/dependency_links.txt
clustertree.egg-info/requires.txt
clustertree.egg-info/top_level.txt
clustertree/src/__init__.py
clustertree/src/cluster.c
clustertree/src/cluster.h
clustertree/src/clustertree.c
clustertree/src/clustertree.pyx