Metadata-Version: 1.0
Name: clustertree
Version: 0.0.4
Summary: Clustertrees.
Home-page: UNKNOWN
Author: Endre Bakken Stovner
Author-email: endrebak85@gmail.com
License: UNKNOWN
Platform: UNKNOWN
